[
    {
        "title": "QuickStop - Juegos de Mesa para Familia y Amigos - Dinámico y Divertido - De 2 a 7 Jugadores - Gran Premio del Juguete 2024 - Regalo Navidad",
        "image": "https://images-eu.ssl-images-amazon.com/images/I/61iWBzV2-8L._AC_UL600_SR600,400_.jpg",
        "url": "https://www.amazon.es/Quick-Stop-Din%C3%A1mico-Creatividad-Entretenida/dp/B0CJ54TF8K/ref=zg_bs_g_toys_d_sccl_1/520-8370060-4603139?psc=1",
        "price": "19,89 €"
    },
    {
        "title": "ATM Gaming Quickstop Family – El Juego de Mesa Más Divertido para Toda la Familia | Rápido, Competitivo Noches en Casa - Regalo Navidad",
        "image": "https://images-eu.ssl-images-amazon.com/images/I/61lHIHD6EQL._AC_UL600_SR600,400_.jpg",
        "url": "https://www.amazon.es/Quickstop-Family-Divertido-Entretenimiento-Pantallas/dp/B0F33P8VJ6/ref=zg_bs_g_toys_d_sccl_2/520-8370060-4603139?psc=1",
        "price": "19,99 €"
    },
    {
        "title": "Hitster Original, Juego de mesa adultos y diviertido, juego de mesa musical, a partir de 16 años, de 2 a 10 jugadores, App gratuita, juego de fiesta, Español (ES)",
        "image": "https://images-eu.ssl-images-amazon.com/images/I/71wGs+uPNYL._AC_UL600_SR600,400_.jpg",
        "url": "https://www.amazon.es/Jumbo-Hitster-Original-Adultos-Jugadores/dp/B0B3RVC43L/ref=zg_bs_g_toys_d_sccl_3/520-8370060-4603139?psc=1",
        "price": "24,97 €"
    },
    {
        "title": "Ludilo - Taco Gato Cabra Queso Pizza | Juegos De Mesa | Juegos De Mesa Niños 8 Años O Más | Juego De Cartas con 60 Cartas | Regalo Niño 8 Años O Más De 3 A 8 Jugadores",
        "image": "https://images-eu.ssl-images-amazon.com/images/I/71CW2OINIyL._AC_UL600_SR600,400_.jpg",
        "url": "https://www.amazon.es/Cabra-Ludilo-Juegos-Cartas-Familiares/dp/B085DTTYP7/ref=zg_bs_g_toys_d_sccl_4/520-8370060-4603139?psc=1",
        "price": "12,49 €"
    },
    {
        "title": "Play Hit - Juegos de Mesa para Adultos, Amigos y Familia - Anima Tus Reuniones y Fiestas con Música en Español - Regalo Navidad Original",
        "image": "https://images-eu.ssl-images-amazon.com/images/I/61xs3qrlN9L._AC_UL600_SR600,400_.jpg",
        "url": "https://www.amazon.es/Play-Hit-Divertido-din%C3%A1mico-Diversi%C3%B3n/dp/B0DG63KMRH/ref=zg_bs_g_toys_d_sccl_5/520-8370060-4603139?psc=1",
        "price": "14,70 €"
    },
    {
        "title": "LEGO Speed Champions Coche de Carreras Aston Martin Aramco F1 AMR24 de Juguete, Maqueta de Vehículo de Fórmula 1 con Minifigura de Piloto, Regalo para Niños y Niñas de 10 Años o Más 77245",
        "image": "https://images-eu.ssl-images-amazon.com/images/I/81OSvFcxU-L._AC_UL600_SR600,400_.jpg",
        "url": "https://www.amazon.es/LEGO-Champions-Carreras-Minifigura-77245/dp/B0DHSDWPP2/ref=zg_bs_g_toys_d_sccl_6/520-8370060-4603139?psc=1",
        "price": "24,65 €"
    },
    {
        "title": "Tranjis Games - Virus! - Juego de cartas, 8 a 99 años (TRG-01vir)",
        "image": "https://images-eu.ssl-images-amazon.com/images/I/61BSkh57s9L._AC_UL600_SR600,400_.jpg",
        "url": "https://www.amazon.es/Tranjis-games-Virus-Cartas-1138753-62/dp/8460659666/ref=zg_bs_g_toys_d_sccl_7/520-8370060-4603139?psc=1",
        "price": "12,99 €"
    },
    {
        "title": "Little Secret - Juego del Impostor y Misterio - Ganador del Gran Premio del Juego 2022 - para Amigos y Familia - Regalo Navidad",
        "image": "https://images-eu.ssl-images-amazon.com/images/I/81+LbN9b8xL._AC_UL600_SR600,400_.jpg",
        "url": "https://www.amazon.es/LITTLE-SECRET-Palabras-Misterio-Diversi%C3%B3n/dp/B0B77CMJXZ/ref=zg_bs_g_toys_d_sccl_8/520-8370060-4603139?psc=1",
        "price": "19,99 €"
    },
    {
        "title": "Bitzee - Mascota Virtual con 30 Personajes De Disney - Mascota Digital Que Reacciona al Tacto, con Interacciones y Sonidos - Regalo Niño 5 Años + - Juguetes Niños 5 Años +",
        "image": "https://images-eu.ssl-images-amazon.com/images/I/81vmruxKzWL._AC_UL600_SR600,400_.jpg",
        "url": "https://www.amazon.es/PERSONAJES-Interactiva-Interacciones-6070083-Infantiles/dp/B0CQN38M8W/ref=zg_bs_g_toys_d_sccl_9/520-8370060-4603139?psc=1",
        "price": "37,93 €"
    },
    {
        "title": "ATM Gaming Guatafamily - Juegos de Mesa Familiar - Divertido para Niños y Adultos - Sin Pantallas - Conexión en Familia - Regalo Navidad",
        "image": "https://images-eu.ssl-images-amazon.com/images/I/71pGlzyIGnL._AC_UL600_SR600,400_.jpg",
        "url": "https://www.amazon.es/ATM-Gaming-Guatafamily-Divertido-Pantallas/dp/B0922BL1DD/ref=zg_bs_g_toys_d_sccl_10/520-8370060-4603139?psc=1",
        "price": "16,99 €"
    },
    {
        "title": "Dreamon Aqua Gelz Set, Juguete de Gel de Agua Mágico 3D DIY, Juego Magic Gel Kit con 22 colores y 16 formas, Regalo de Juguete Creativo para niños de 3 años en Adelante, niños y niñas",
        "image": "https://images-eu.ssl-images-amazon.com/images/I/811s5oiq4DL._AC_UL600_SR600,400_.jpg",
        "url": "https://www.amazon.es/Dreamon-Juguete-colores-Creativo-Adelante/dp/B0DS1Q4M4J/ref=zg_bs_g_toys_d_sccl_11/520-8370060-4603139?psc=1",
        "price": "28,72 €"
    },
    {
        "title": "Fede Karaoke 2 Micrófonos para Niños, Mini Karaoke Infantil Micrófonos Inalámbricos Altavoz Bluetooth Portátil con Efectos de Cambio de Voz y Luces LED, Mejores Juguetes Regalos para Niñas y Niños",
        "image": "https://images-eu.ssl-images-amazon.com/images/I/71SwlWrn9CL._AC_UL600_SR600,400_.jpg",
        "url": "https://www.amazon.es/Fede-Micr%C3%B3fonos-Infantil-Inal%C3%A1mbricos-Bluetooth/dp/B0CT95Z6HR/ref=zg_bs_g_toys_d_sccl_12/520-8370060-4603139?psc=1",
        "price": "19,99 €"
    },
    {
        "title": "Nancy Aitana Alphahouse, Muñeca como la Cantante, Melena Oscura con Corte a Capas, Conjunto Diseñado por JC Pajares, Hoja de Tatuajes de Aitana, Certificado de Autenticidad, 3+ años, Famosa (NAC85000)",
        "image": "https://images-eu.ssl-images-amazon.com/images/I/81qScRTEFGL._AC_UL600_SR600,400_.jpg",
        "url": "https://www.amazon.es/Nancy-Alphahouse-Certificado-Autenticidad-NAC85000/dp/B0DHZCN2B6/ref=zg_bs_g_toys_d_sccl_13/520-8370060-4603139?psc=1",
        "price": "14,99 €"
    },
    {
        "title": "RUBIK'S - Rubiks Race Game: Juego de Mesa Clásico de Secuencias Lógicas Uno contra Uno para Dos Jugadores - 6066927 - Juegos de Mesa para Niños 8 años + - Juguetes Niños 8 años +",
        "image": "https://images-eu.ssl-images-amazon.com/images/I/81NlAXpV0vL._AC_UL600_SR600,400_.jpg",
        "url": "https://www.amazon.es/RUBIKS-Cl%C3%A1sico-Secuencias-Jugadores-Juguetes/dp/B0BJ2D2GXX/ref=zg_bs_g_toys_d_sccl_14/520-8370060-4603139?psc=1",
        "price": "19,49 €"
    },
    {
        "title": "Clementoni - 18779 - Idea - Taller De Los Bolígrafos - Un Set Perfecto Para Hacer Tus Propias Bolígrafos, Juego Creativo, Juego Para Manualidades, Juguete 6 Años",
        "image": "https://images-eu.ssl-images-amazon.com/images/I/81k53ZrdHPL._AC_UL600_SR600,400_.jpg",
        "url": "https://www.amazon.es/Clementoni-Bol%C3%ADgrafos-Propias-Creativo-Manualidades/dp/B0C3XL1HZ5/ref=zg_bs_g_toys_d_sccl_15/520-8370060-4603139?psc=1",
        "price": "27,52 €"
    },
    {
        "title": "Play-Doh Hasbro Peluquería, Manualidades para Niñas y Niños a Partir de 3 Años, Set con Herramientas y 6 Botes de Plastilina de Colores, Regalo Creativo",
        "image": "https://images-eu.ssl-images-amazon.com/images/I/71QZYR-6PkL._AC_UL600_SR600,400_.jpg",
        "url": "https://www.amazon.es/Play-Doh-Peluquer%C3%ADa-Estilo-Juguetes-creativos/dp/B0C34RZ84M/ref=zg_bs_g_toys_d_sccl_16/520-8370060-4603139?psc=1",
        "price": "17,40 €"
    },
    {
        "title": "Chicos - Bingo Lotería automática | Incluye 48 cartones, 90 bolas imborrables y fichas de juego |Un juego de siempre para toda la familia | Medidas: 235 x 310 x 17 mm (20805)",
        "image": "https://images-eu.ssl-images-amazon.com/images/I/81+783f4gIL._AC_UL600_SR600,400_.jpg",
        "url": "https://www.amazon.es/Chicos-autom%C3%A1tica-cartones-Juguetes-20805/dp/B012Z8BE5E/ref=zg_bs_g_toys_d_sccl_17/520-8370060-4603139?psc=1",
        "price": "23,09 €"
    },
    {
        "title": "PILI PILI – Juego de Mesa Rápido y Estratégico | para Familia y Amigos – 2 a 8 Jugadores – Ganador del Gran Premio del Juguete 2025 - Regalo Navidad",
        "image": "https://images-eu.ssl-images-amazon.com/images/I/71HEpQ8mI2L._AC_UL600_SR600,400_.jpg",
        "url": "https://www.amazon.es/PILI-Estrat%C3%A9gico-Familia-Jugadores-Ganador/dp/B0FBMDZY83/ref=zg_bs_g_toys_d_sccl_18/520-8370060-4603139?psc=1",
        "price": "14,99 €"
    },
    {
        "title": "Goula Los 3 Cerditos: Juego de Mesa Educativo Preescolar para Niños a Partir de 2 Años, Juego Infantil de 1 a 4 Jugadores con Piezas de Madera y Tablero Puzle - Juguetes Niños 2 Años",
        "image": "https://images-eu.ssl-images-amazon.com/images/I/71X8K3cOJtL._AC_UL600_SR600,400_.jpg",
        "url": "https://www.amazon.es/Goula-Juego-los-cerditos-53146/dp/B07B37TT7F/ref=zg_bs_g_toys_d_sccl_19/520-8370060-4603139?psc=1",
        "price": "15,99 €"
    },
    {
        "title": "Walkie Talkie Niños Recargable, 48 Horas de Tiempo de Trabajo, 3 kilómetros de Largo Alcance,JRegalo de Juguetes al Aire Libre para niños de 3 a 12 años, Paquete de 3",
        "image": "https://images-eu.ssl-images-amazon.com/images/I/71bUFwANmjL._AC_UL600_SR600,400_.jpg",
        "url": "https://www.amazon.es/Recargable-Trabajo-kil%C3%B3metros-Alcance-Juguetes/dp/B0CT3B1SRY/ref=zg_bs_g_toys_d_sccl_20/520-8370060-4603139?psc=1",
        "price": "30,99 €"
    },
    {
        "title": "TOSY Magnet Fidget Spinner Glow - 16 Bloques: Fidget Spinner transformable, Cubo Infinito/Rompecabezas, Brillante, niños y Adultos, Juguete sensorial Stem",
        "image": "https://images-eu.ssl-images-amazon.com/images/I/81dQ70Pc2oL._AC_UL600_SR600,400_.jpg",
        "url": "https://www.amazon.es/TOSY-Magnet-Fidget-Spinner-Glow/dp/B0DMPFLN3B/ref=zg_bs_g_toys_d_sccl_21/520-8370060-4603139?psc=1",
        "price": "25,99 €"
    },
    {
        "title": "Bizak Juego Pedrete el Mono Guarrete, Multicolor, Única",
        "image": "https://images-eu.ssl-images-amazon.com/images/I/81aXG3kkt9L._AC_UL600_SR600,400_.jpg",
        "url": "https://www.amazon.es/Tricky-Juegos-Pedrete-Guarrete-62468742/dp/B07D9DKSX8/ref=zg_bs_g_toys_d_sccl_22/520-8370060-4603139?psc=1",
        "price": "35,99 €"
    },
    {
        "title": "Diset",
        "image": "https://images-eu.ssl-images-amazon.com/images/I/81tStul3-oL._AC_UL300_SR300,200_.jpg",
        "url": "https://www.amazon.es/Diset-Malet%C3%ADn-aprendo-Leer-63715/dp/B0068A96N8/ref=zg_bs_g_toys_d_sccl_23/520-8370060-4603139?psc=1",
        "price": "19,95 €"
    },
    {
        "title": "Mattel Games - UNO Original - Juego de Cartas Familiar - Clásico - Baraja Multicolor de 112 Cartas - De 2 a 10 Jugadores - para Niños y Adultos - Regalo para 7+ Años, W2087",
        "image": "https://images-eu.ssl-images-amazon.com/images/I/71IC1KLr+uL._AC_UL600_SR600,400_.jpg",
        "url": "https://www.amazon.es/Mattel-Games-classic-cartas-W2087/dp/B005I5M2F8/ref=zg_bs_g_toys_d_sccl_24/520-8370060-4603139?psc=1",
        "price": "7,99 €"
    },
    {
        "title": "Hot Bee Kit de Gel de Agua Mágico para Niños - 10 Botellas, 8 Doble Moldes, Juguetes Niñas Magic Water Aqua Fairy Manualidades Aqua Gelz Regalo Ideal para de 4 a 10 Años Juegos Agua",
        "image": "https://images-eu.ssl-images-amazon.com/images/I/81LnY42BsBL._AC_UL600_SR600,400_.jpg",
        "url": "https://www.amazon.es/Hot-Bee-Agua-M%C3%A1gico-Ni%C3%B1os/dp/B0F59PWTNV/ref=zg_bs_g_toys_d_sccl_25/520-8370060-4603139?psc=1",
        "price": "25,99 €"
    },
    {
        "title": "CRAYOLA - Laboratorio de Rotuladores Olorosos Neón, Crea tus Propios Rotuladores Perfumados con Colores Neón, Actividad Creativa y Regalo para Niños, a Partir de 6 Años (Versión en español)",
        "image": "https://images-eu.ssl-images-amazon.com/images/I/71d-CB-olDL._AC_UL600_SR600,400_.jpg",
        "url": "https://www.amazon.es/CRAYOLA-Laboratorio-Rotuladores-Perfumados-Actividad/dp/B0BQJSVPZR/ref=zg_bs_g_toys_d_sccl_26/520-8370060-4603139?psc=1",
        "price": "25,99 €"
    },
    {
        "title": "Diset - Lectron Lapiz Temas De Logica, Juego educativo de asociar preguntas y respuestas a partir de 3 años",
        "image": "https://images-eu.ssl-images-amazon.com/images/I/711nz3n1PUL._AC_UL600_SR600,400_.jpg",
        "url": "https://www.amazon.es/Diset-63882-Lectron-Lapiz-Logica/dp/B0068A97VY/ref=zg_bs_g_toys_d_sccl_27/520-8370060-4603139?psc=1",
        "price": "14,99 €"
    },
    {
        "title": "Lisciani - Baby Memo - Los Animales - Juego de Sociedad Educativo - Juego de Memoria y Reflexión - 24 Cartas - Para Niños de 1 a 4 años de edad - CAROTINA BABY",
        "image": "https://images-eu.ssl-images-amazon.com/images/I/81V0Ishx87L._AC_UL600_SR600,400_.jpg",
        "url": "https://www.amazon.es/Lisciani-Animales-Sociedad-Educativo-Reflexi%C3%B3n/dp/B0843R4NGJ/ref=zg_bs_g_toys_d_sccl_28/520-8370060-4603139?psc=1",
        "price": "6,99 €"
    },
    {
        "title": "Bloques Magnéticos de Construcción Juguete Educativo Montessori para Niños y Niñas de 2 y 3 Años Bloques Magnéticos para Construcción Infantil Juguetes para Niños 2 Años Juguetes para Niños 3 Años",
        "image": "https://images-eu.ssl-images-amazon.com/images/I/81Q7GtEiP8L._AC_UL600_SR600,400_.jpg",
        "url": "https://www.amazon.es/Magn%C3%A9ticos-Construcci%C3%B3n-Educativo-Montessori-Infantil/dp/B0BGLTYW59/ref=zg_bs_g_toys_d_sccl_29/520-8370060-4603139?psc=1",
        "price": "24,99 €"
    },
    {
        "title": "Spin Master Games - Juego DE Mesa Hijos contra Padres: Divertidas Pruebas y Preguntas para Toda la Familia, 2-6 Jugadores - 6065093 - Juegos de Mesa Niños 6 años + - Regalo Niño 6 años +",
        "image": "https://images-eu.ssl-images-amazon.com/images/I/81SPNFy+hhL._AC_UL600_SR600,400_.jpg",
        "url": "https://www.amazon.es/JUEGOS-MESA-Preguntas-Familias-jugadores/dp/B09M4YFK99/ref=zg_bs_g_toys_d_sccl_30/520-8370060-4603139?psc=1",
        "price": "13,49 €"
    },
    {
        "title": "Devir - Código Secreto, Juego de Mesa de Espías y Palabras por Equipos, Estrategia y Deducción, para 2-8 Jugadores, a Partir de 8 Años, Portada 2025 (BGCOSE)",
        "image": "https://images-eu.ssl-images-amazon.com/images/I/71d2yhkiUXL._AC_UL300_SR300,200_.jpg",
        "url": "https://www.amazon.es/Devir-C%C3%B3digo-Secreto-Juego-BGCOSE/dp/B019M2EA3Y/ref=zg_bs_g_toys_d_sccl_31/520-8370060-4603139?psc=1",
        "price": "22,49 €"
    },
    {
        "title": "Play-Doh Hasbro Swirlin’ Smoothies, Batidora de Juguete para Niños y Niñas de 3 Años o Más, Juegos de Cocina, Manualidades Creativas",
        "image": "https://images-eu.ssl-images-amazon.com/images/I/712ZSe3sBsL._AC_UL300_SR300,200_.jpg",
        "url": "https://www.amazon.es/Play-Doh-Licuadora-Coloridos-Actividades-Manualidades/dp/B0C3528VHM/ref=zg_bs_g_toys_d_sccl_32/520-8370060-4603139?psc=1",
        "price": "9,99 €"
    },
    {
        "title": "60 piezas de azulejos magnéticos de construcción – Bloques magnéticos STEM para niños, juguetes sensoriales para niños y niñas a partir de 3 años, desarrollo cerebral, preescolar, jardín de infantes",
        "image": "https://images-eu.ssl-images-amazon.com/images/I/81Pqp5Sn50L._AC_UL300_SR300,200_.jpg",
        "url": "https://www.amazon.es/Coodoo-Bloques-construcci%C3%B3n-magn%C3%A9ticos-azulejos/dp/B0BVFMWMVP/ref=zg_bs_g_toys_d_sccl_33/520-8370060-4603139?psc=1",
        "price": "34,99 €"
    },
    {
        "title": "Devir - Catan | Juego de Mesa de Estrategia y Comercio, 3-4 jugadores, Juego Clásico Familiar y con Amigos, Recursos y Negociación para Familia y Amigos, Nueva Portada 2025 (BGCATAN)",
        "image": "https://images-eu.ssl-images-amazon.com/images/I/71p52Zx4RTL._AC_UL300_SR300,200_.jpg",
        "url": "https://www.amazon.es/Devir-Catan-juego-mesa-BGCATAN/dp/B006CZ0LGA/ref=zg_bs_g_toys_d_sccl_34/520-8370060-4603139?psc=1",
        "price": "37,86 €"
    },
    {
        "title": "Falomir - Juego de Mesa ¿Qué Soy Yo? | Mejora Vocabulario y Desarrollo Motriz | Intelectual | Sensitivo | Edad 7 Años | Perfecto parta Jugar en Familia",
        "image": "https://images-eu.ssl-images-amazon.com/images/I/81apnHVkQCL._AC_UL300_SR300,200_.jpg",
        "url": "https://www.amazon.es/Falomir-646468-Juego-Que-Soy/dp/B005OQB3BK/ref=zg_bs_g_toys_d_sccl_35/520-8370060-4603139?psc=1",
        "price": "9,47 €"
    },
    {
        "title": "Lisciani Giochi - Escuela de dibujo con proyector de PRINCESAS DISNEY - Para niños a partir de 3 años - Aprende a dibujar con modelos proyectados - Incluye modelos, papel y lápices - Juego creativo",
        "image": "https://images-eu.ssl-images-amazon.com/images/I/81JYsIJuIsL._AC_UL300_SR300,200_.jpg",
        "url": "https://www.amazon.es/Lisciani-Princesa-Proiettore-Drawing-92956/dp/B0B5GKV1V6/ref=zg_bs_g_toys_d_sccl_36/520-8370060-4603139?psc=1",
        "price": "29,95 €"
    },
    {
        "title": "Hasbro Gaming, Monopoly Clásico, Juego de Mesa, Inversión en Familia, Tablero, Caja Almacenamiento, 6 Peones Grandes, Fiestas con Amigos, Multijugador, Dinero Colores, Juegos de Navidad y Papa Noel",
        "image": "https://images-eu.ssl-images-amazon.com/images/I/71WuJJXWg5L._AC_UL300_SR300,200_.jpg",
        "url": "https://www.amazon.es/Monopoly-cl%C3%A1sico-Bandeja-Almacenamiento-Grandes/dp/B0DM97GPGL/ref=zg_bs_g_toys_d_sccl_37/520-8370060-4603139?psc=1",
        "price": "26,59 €"
    },
    {
        "title": "Ludilo - Batalla De Genios Original | Juegos De Mesa Niños 6 Años O Más | Juegos De Mesa Niños Y Adultos | Juguetes 6 Años De 2 Jugadores | Rompecabezas Adultos con Mas De 60.000 Combinaciones",
        "image": "https://images-eu.ssl-images-amazon.com/images/I/71wgtxHmP4L._AC_UL300_SR300,200_.jpg",
        "url": "https://www.amazon.es/Ludilo-Batalla-Original-Juguetes-Regalos/dp/B07X4B2TWY/ref=zg_bs_g_toys_d_sccl_38/520-8370060-4603139?psc=1",
        "price": "26,43 €"
    },
    {
        "title": "PERPLEXUS - Rompecabezas PERPLEXUS Epic: Bola Laberinto 3D con 125 Obstáculos - 6053141 - Juguetes Niños 10 años +",
        "image": "https://images-eu.ssl-images-amazon.com/images/I/81Fq4k9X2iL._AC_UL300_SR300,200_.jpg",
        "url": "https://www.amazon.es/PERPLEXUS-Rompecabezas-Laberinto-Obst%C3%A1culos-Juguetes/dp/B07MGRNKBT/ref=zg_bs_g_toys_d_sccl_39/520-8370060-4603139?psc=1",
        "price": "28,99 €"
    },
    {
        "title": "LEGO Creator 3 en 1 Fauna Salvaje: Flamenco Rosa de Juguete - Transformable en Cacatúa o Ajolote - Juego con Figuras Articuladas de Animales - Regalo de Cumpleaños para Niñas y Niños de 8+ Años 31170",
        "image": "https://images-eu.ssl-images-amazon.com/images/I/81tpwwwTqHL._AC_UL300_SR300,200_.jpg",
        "url": "https://www.amazon.es/LEGO-Creator-Fauna-Salvaje-Transformable/dp/B0DHSGF8FD/ref=zg_bs_g_toys_d_sccl_40/520-8370060-4603139?psc=1",
        "price": "19,99 €"
    },
    {
        "title": "Bizak Boli Loco, Multicolor, Juego de 156 Piezas",
        "image": "https://images-eu.ssl-images-amazon.com/images/I/61MUb6WPx6L._AC_UL300_SR300,200_.jpg",
        "url": "https://www.amazon.es/Juegos-Bizak-Boli-Multicolor-63391801/dp/B07SHHFPVX/ref=zg_bs_g_toys_d_sccl_41/520-8370060-4603139?psc=1",
        "price": "29,96 €"
    },
    {
        "title": "TOSY Magnet Pyramid Stone: 1 Cubo se transforma en mil Millones de Formas, 243 imanes, diseño holográfico, Accesorio Giratorio, Juguete Steam, Regalo de cumpleaños",
        "image": "https://images-eu.ssl-images-amazon.com/images/I/81uMwvkWmHL._AC_UL300_SR300,200_.jpg",
        "url": "https://www.amazon.es/TOSY-Magnet-Pyramid-Stone-hologr%C3%A1fico/dp/B0DMSVXBDV/ref=zg_bs_g_toys_d_sccl_42/520-8370060-4603139?psc=1",
        "price": "27,99 €"
    },
    {
        "title": "Bey Blade BBX Arrow Wizard Stamina",
        "image": "https://images-eu.ssl-images-amazon.com/images/I/81nvXmsDrRL._AC_UL300_SR300,200_.jpg",
        "url": "https://www.amazon.es/Hasbro-Beyblade-Wizard-Stamina-5010996257116/dp/B0CP66TLRY/ref=zg_bs_g_toys_d_sccl_43/520-8370060-4603139?psc=1",
        "price": "9,99 €"
    },
    {
        "title": "BONNYCO Busy Board Montessori de Fieltro, Maletin de Paneles Sensoriales Montessori. Tablero Busy Book, Juguetes Educativos Motricidad Fina. Juguetes Regalos para Niños y Niñas Cumpleaños, Navidad",
        "image": "https://images-eu.ssl-images-amazon.com/images/I/91CnHVe2PkL._AC_UL300_SR300,200_.jpg",
        "url": "https://www.amazon.es/BONNYCO-Montessori-Sensoriales-Educativos-Motricidad/dp/B0CQ2XBTSB/ref=zg_bs_g_toys_d_sccl_44/520-8370060-4603139?psc=1",
        "price": "20,99 €"
    },
    {
        "title": "Science4you Robotics Betabot - Kit Robotica de 126 Piezas, Construye tu Robot Interactivo, Juegos de Construcciones, Juguetes de Montar, Regalos para Niños y Niñas de 8 9 10+ años",
        "image": "https://images-eu.ssl-images-amazon.com/images/I/71-zTuslsDL._AC_UL300_SR300,200_.jpg",
        "url": "https://www.amazon.es/Science4you-cient%C3%ADfico-Educativo-Multicolor-605152/dp/B07B42X1Z3/ref=zg_bs_g_toys_d_sccl_45/520-8370060-4603139?psc=1",
        "price": "14,99 €"
    },
    {
        "title": "Devir - Sushi Go, Juego de Cartas, Juego de Mesa con Amigos y para Fiestas, a Partir de 8 años (BGSUSHI)",
        "image": "https://images-eu.ssl-images-amazon.com/images/I/71TY3fEY5CL._AC_UL300_SR300,200_.jpg",
        "url": "https://www.amazon.es/Devir-221855-Sushi-Go-BGSUSHI/dp/B00PY78UCO/ref=zg_bs_g_toys_d_sccl_46/520-8370060-4603139?psc=1",
        "price": "9,99 €"
    },
    {
        "title": "Disney Store Official, Toy Story de Pixar, Sheriff Woody, Figura acción interactiva parlante, 39 cm, muñeco Vaquero Cuerda y 15 Frases en inglés, interactúa con más Personajes, para Mayores de 3 años",
        "image": "https://images-eu.ssl-images-amazon.com/images/I/71996FN137L._AC_UL300_SR300,200_.jpg",
        "url": "https://www.amazon.es/Disney-Store-interactiva-interact%C3%BAa-Personajes/dp/B0DLH5JYBD/ref=zg_bs_g_toys_d_sccl_47/520-8370060-4603139?psc=1",
        "price": "69,00 €"
    },
    {
        "title": "Beyblade X, Kit Inicial Lance Knight 4-80HN con Top y Lanzador",
        "image": "https://images-eu.ssl-images-amazon.com/images/I/71q7LuNXrvL._AC_UL300_SR300,200_.jpg",
        "url": "https://www.amazon.es/Beyblade-Inicial-Knight-4-80HN-Lanzador/dp/B0D87R1Z2C/ref=zg_bs_g_toys_d_sccl_48/520-8370060-4603139?psc=1",
        "price": "9,99 €"
    },
    {
        "title": "Shashibo Rompecabezas para Niños - Premiado Cubo Magnético Patentado con 36 Imanes de Tierras Raras - Asombroso Rompecabezas 3D – Juguete para Adultos Cubo 100 Formas (Spaced out)",
        "image": "https://images-eu.ssl-images-amazon.com/images/I/71wb8VrCbVL._AC_UL300_SR300,200_.jpg",
        "url": "https://www.amazon.es/Shashibo-Rompecabezas-para-Ni%C3%B1os-Magn%C3%A9tico/dp/B07W5QM4DP/ref=zg_bs_g_toys_d_sccl_49/520-8370060-4603139?psc=1",
        "price": "24,99 €"
    },
    {
        "title": "Gafas VR HeroMask + Juegos Matemáticas 5-12 años — El Regalo Educativo Que Hace Que los niños pidan: ¿5 Minutos más? | Tablas de Multiplicar, Sumas, Cálculo Mental y Mucho más | 3D, Realidad Virtual",
        "image": "https://images-eu.ssl-images-amazon.com/images/I/810S6OcvXBL._AC_UL300_SR300,200_.jpg",
        "url": "https://www.amazon.es/HeroMask-Matem%C3%A1ticas-Aprendizaje-diversi%C3%B3n-%C2%A1Sorpr%C3%A9ndele/dp/B07VSMGN9H/ref=zg_bs_g_toys_d_sccl_50/520-8370060-4603139?psc=1",
        "price": "57,00 €"
    }
]